inactivity/__init__.py
inactivity/admin.py
inactivity/app_settings.py
inactivity/apps.py
inactivity/auth_hooks.py
inactivity/forms.py
inactivity/helpers.py
inactivity/managers.py
inactivity/models.py
inactivity/tasks.py
inactivity/urls.py
inactivity/views.py
inactivity/migrations/0001_initial.py
inactivity/migrations/0002_add_manage_leave_perm.py
inactivity/migrations/0003_add_webhooks.py
inactivity/migrations/0004_django4_update.py
inactivity/migrations/0005_various_improvements.py
inactivity/migrations/0006_alter_webhook_notification_types.py
inactivity/migrations/__init__.py
inactivity/static/inactivity/css/aa-bootstrap-fix.css
inactivity/static/inactivity/css/aa-bootstrap-fix.min.css
inactivity/static/inactivity/css/inactivity.css
inactivity/static/inactivity/css/manage_requests.css
inactivity/static/inactivity/css/my_requests.css
inactivity/static/inactivity/images/Spinner-1s-64px-dark.gif
inactivity/static/inactivity/images/Spinner-1s-64px-light.gif
inactivity/templates/inactivity/base.html
inactivity/templates/inactivity/create_loa.html
inactivity/templates/inactivity/inactive_users.html
inactivity/templates/inactivity/manage_requests.html
inactivity/templates/inactivity/my_requests.html
inactivity/templates/inactivity/reject_request.html
inactivity/templates/inactivity/modals/modal_dialog.html
inactivity/templates/inactivity/modals/view_request_content.html
inactivity/tests/__init__.py
inactivity/tests/factories.py
inactivity/tests/test_forms.py
inactivity/tests/test_integration.py
inactivity/tests/test_managers.py
inactivity/tests/test_models.py
inactivity/tests/test_tasks.py
inactivity/tests/test_views.py
aa_inactivity-2.0.1.dist-info/licenses/LICENSE
aa_inactivity-2.0.1.dist-info/WHEEL
aa_inactivity-2.0.1.dist-info/METADATA
aa_inactivity-2.0.1.dist-info/RECORD
